huaweicloudsdkroma/__init__.py
huaweicloudsdkroma/v2/__init__.py
huaweicloudsdkroma/v2/roma_async_client.py
huaweicloudsdkroma/v2/roma_client.py
huaweicloudsdkroma/v2/model/__init__.py
huaweicloudsdkroma/v2/model/acl_api_binding_create.py
huaweicloudsdkroma/v2/model/acl_api_binding_info.py
huaweicloudsdkroma/v2/model/acl_batch_delete.py
huaweicloudsdkroma/v2/model/acl_batch_failure.py
huaweicloudsdkroma/v2/model/acl_bind_api_info.py
huaweicloudsdkroma/v2/model/acl_binding_batch_delete.py
huaweicloudsdkroma/v2/model/acl_binding_batch_failure.py
huaweicloudsdkroma/v2/model/add_subsets_to_gateway_request.py
huaweicloudsdkroma/v2/model/add_subsets_to_gateway_request_body.py
huaweicloudsdkroma/v2/model/add_subsets_to_gateway_response.py
huaweicloudsdkroma/v2/model/add_subsets_to_gateway_response_body.py
huaweicloudsdkroma/v2/model/add_user_to_app.py
huaweicloudsdkroma/v2/model/add_user_to_app_request.py
huaweicloudsdkroma/v2/model/add_user_to_app_response.py
huaweicloudsdkroma/v2/model/adding_backend_instances_v2_request.py
huaweicloudsdkroma/v2/model/adding_backend_instances_v2_response.py
huaweicloudsdkroma/v2/model/api_acl_create.py
huaweicloudsdkroma/v2/model/api_acl_info_with_bind_num.py
huaweicloudsdkroma/v2/model/api_action_info.py
huaweicloudsdkroma/v2/model/api_auth_base.py
huaweicloudsdkroma/v2/model/api_auth_create.py
huaweicloudsdkroma/v2/model/api_auth_detail.py
huaweicloudsdkroma/v2/model/api_auth_info.py
huaweicloudsdkroma/v2/model/api_auth_relations.py
huaweicloudsdkroma/v2/model/api_auth_visit_param.py
huaweicloudsdkroma/v2/model/api_base_info.py
huaweicloudsdkroma/v2/model/api_batch_publish.py
huaweicloudsdkroma/v2/model/api_bind_acl_info.py
huaweicloudsdkroma/v2/model/api_check_info.py
huaweicloudsdkroma/v2/model/api_check_info_v2.py
huaweicloudsdkroma/v2/model/api_common.py
huaweicloudsdkroma/v2/model/api_condition_base.py
huaweicloudsdkroma/v2/model/api_condition_create.py
huaweicloudsdkroma/v2/model/api_create.py
huaweicloudsdkroma-3.1.184.dist-info/METADATA
huaweicloudsdkroma-3.1.184.dist-info/WHEEL
huaweicloudsdkroma-3.1.184.dist-info/licenses/LICENSE
huaweicloudsdkroma-3.1.184.dist-info/RECORD
